nonebot_plugin_clovers/__init__.py
nonebot_plugin_clovers/adapters/onebot/v11.py
nonebot_plugin_clovers/adapters/qq/general.py
nonebot_plugin_clovers/adapters/qq/group.py
nonebot_plugin_clovers/adapters/qq/guild.py
nonebot_plugin_clovers/adapters/satori/__init__.py
nonebot_plugin_clovers/adapters/typing.py
nonebot_plugin_clovers/adapters/uninfo/__init__.py
nonebot_plugin_clovers/adapters/uninfo/utils.py
nonebot_plugin_clovers/clovers.py
nonebot_plugin_clovers/config.py
nonebot_plugin_clovers-0.3.6.dist-info/LICENSE
nonebot_plugin_clovers-0.3.6.dist-info/METADATA
nonebot_plugin_clovers-0.3.6.dist-info/WHEEL
nonebot_plugin_clovers-0.3.6.dist-info/RECORD
