Metadata-Version: 2.3
Name: nonebot-plugin-clovers
Version: 0.3.6
Summary: 
Author: KarisAya
Author-email: karisaya@foxmail.com
Requires-Python: >=3.12,<4.0
Classifier: Programming Language :: Python :: 3
Classifier: Programming Language :: Python :: 3.12
Classifier: Programming Language :: Python :: 3.13
Provides-Extra: nonebot-adapter-onebot
Provides-Extra: nonebot-adapter-qq
Provides-Extra: nonebot-adapter-satori
Provides-Extra: uninfo
Requires-Dist: clovers (>=0.4.6,<0.5.0)
Requires-Dist: nonebot-adapter-onebot (>=2.4.6,<3.0.0) ; extra == "nonebot-adapter-onebot"
Requires-Dist: nonebot-adapter-qq (>=1.6.1,<2.0.0) ; extra == "nonebot-adapter-qq"
Requires-Dist: nonebot-adapter-satori (>=0.13.3,<1.0.0) ; extra == "nonebot-adapter-satori"
Requires-Dist: nonebot-plugin-alconna (>=0.58.5,<1.0.0) ; extra == "uninfo"
Requires-Dist: nonebot-plugin-uninfo (>=0.8.2,<1.0.0) ; extra == "uninfo"
Requires-Dist: nonebot2 (>=2.4.2,<3.0.0)
Requires-Dist: pydantic (>=2.11.4,<3.0.0)
